csv23/__init__.py
csv23/_common.py
csv23/_dispatch.py
csv23/_workarounds.py
csv23/dialects.py
csv23/extras.py
csv23/openers.py
csv23/readers.py
csv23/shortcuts.py
csv23/writers.py
csv23-0.3.4.dist-info/LICENSE.txt
csv23-0.3.4.dist-info/METADATA
csv23-0.3.4.dist-info/WHEEL
csv23-0.3.4.dist-info/top_level.txt
csv23-0.3.4.dist-info/RECORD
