Metadata-Version: 2.1
Name: csv23
Version: 0.3.4
Summary: Python 2/3 unicode CSV compatibility layer
Home-page: https://github.com/xflr6/csv23
Author: Sebastian Bank
Author-email: sebastian.bank@uni-leipzig.de
License: MIT
Project-URL: Documentation, https://csv23.readthedocs.io
Project-URL: Changelog, https://csv23.readthedocs.io/en/latest/changelog.html
Project-URL: Issue Tracker, https://github.com/xflr6/csv23/issues
Project-URL: CI, https://github.com/xflr6/csv23/actions
Project-URL: Coverage, https://codecov.io/gh/xflr6/csv23
Keywords: unicode csv reader writer
Platform: any
Classifier: Development Status :: 4 - Beta
Classifier: Intended Audience :: Developers
Classifier: Intended Audience :: Science/Research
Classifier: License :: OSI Approved :: MIT License
Classifier: Operating System :: OS Independent
Classifier: Programming Language :: Python :: 2
Classifier: Programming Language :: Python :: 2.7
Classifier: Programming Language :: Python :: 3
Classifier: Programming Language :: Python :: 3.7
Classifier: Programming Language :: Python :: 3.8
Classifier: Programming Language :: Python :: 3.9
Classifier: Programming Language :: Python :: 3.10
Requires-Python: >=2.7,!=3.0.*,!=3.1.*,!=3.2.*,!=3.3.*,!=3.4.*,!=3.5.*,!=3.6.*
Provides-Extra: dev
Provides-Extra: test
Provides-Extra: docs
License-File: LICENSE.txt
